knip.py
knip-0.0.3.dist-info/METADATA
knip-0.0.3.dist-info/RECORD
knip-0.0.3.dist-info/WHEEL
knip-0.0.3.dist-info/top_level.txt
